heya/__init__.py
heya/__main__.py
heya/bin/__init__.py
heya/bin/base.py
heya/bin/heya.py
heya/bin/html2pdf.py
heya/bin/md2pdf.py
heya/bin/mkdocs.yml
heya/pdf/__init__.py
heya/pdf/compress.py
heya/pdf/converter.py
heya-0.0.2.dist-info/LICENSE
heya-0.0.2.dist-info/METADATA
heya-0.0.2.dist-info/WHEEL
heya-0.0.2.dist-info/entry_points.txt
heya-0.0.2.dist-info/RECORD
